Golden.cpython-313-x86_64-linux-gnu.so
entryIterator.py
golden_seq_retriever-3.4.4.post1.dist-info/METADATA
golden_seq_retriever-3.4.4.post1.dist-info/WHEEL
golden_seq_retriever-3.4.4.post1.dist-info/top_level.txt
golden_seq_retriever-3.4.4.post1.dist-info/RECORD
