Metadata-Version: 2.4
Name: golden_seq_retriever
Version: 3.4.4.post1
Summary: Python bindings for the golden tool
Home-page: https://github.com/VeroniqueLegrand/golden
Author: Nicolas Joly, Veronique Legrand
Author-email: vlegrand@pasteur.fr
Dynamic: author
Dynamic: author-email
Dynamic: home-page
Dynamic: summary
